{"cameraMode":{"drawMode":0,"name":"Shaded","section":"Shading Mode"},"sceneLighting":true,"audioPlay":false,"sceneViewState":{"showFog":true,"showMaterialUpdate":false,"showSkybox":true,"showFlares":true,"showImageEffects":true,"showParticleSystems":true},"in2DMode":false,"pivot":{"x":2.3458354473114015,"y":3.998513698577881,"z":3.7000443935394289},"rotation":{"x":-0.00934031791985035,"y":0.9825043678283691,"z":-0.05133351311087608,"w":-0.17878593504428864},"size":3.2824647426605226,"orthographic":false}